tachyon_platform/__init__.py
tachyon_platform/api/__init__.py
tachyon_platform/api/app_containers_api.py
tachyon_platform/api/container_images_api.py
tachyon_platform/api/dashboards_api.py
tachyon_platform/api/datasets_api.py
tachyon_platform/api/dbt_projects_api.py
tachyon_platform/api/files_api.py
tachyon_platform/api/pipelines_api.py
tachyon_platform/api/roles_api.py
tachyon_platform/api/secrets_api.py
tachyon_platform/api/service_principals_api.py
tachyon_platform/api/subscriptions_api.py
tachyon_platform/api/users_api.py
tachyon_platform/api/workspaces_api.py
tachyon_platform/api_client.py
tachyon_platform/api_response.py
tachyon_platform/auth.py
tachyon_platform/configuration.py
tachyon_platform/exceptions.py
tachyon_platform/models/__init__.py
tachyon_platform/models/app_container.py
tachyon_platform/models/app_container_auth.py
tachyon_platform/models/app_container_auth_api.py
tachyon_platform/models/app_container_auth_frontend.py
tachyon_platform/models/app_container_container.py
tachyon_platform/models/app_container_container_env_inner.py
tachyon_platform/models/app_container_container_secret_inner.py
tachyon_platform/models/app_container_create.py
tachyon_platform/models/app_container_paging_list.py
tachyon_platform/models/app_container_port.py
tachyon_platform/models/app_container_resource_requirements.py
tachyon_platform/models/app_container_scaling.py
tachyon_platform/models/app_container_version.py
tachyon_platform/models/app_container_version_create.py
tachyon_platform/models/app_container_version_paging_list.py
tachyon_platform/models/app_container_vpc_access.py
tachyon_platform/models/bad_request_error.py
tachyon_platform/models/conflict_error.py
tachyon_platform/models/container_image_access_token.py
tachyon_platform/models/dashboard.py
tachyon_platform/models/dashboard_list.py
tachyon_platform/models/dashboard_superset_user.py
tachyon_platform/models/dataset.py
tachyon_platform/models/dataset_clustering.py
tachyon_platform-0.2.1.dist-info/METADATA
tachyon_platform-0.2.1.dist-info/WHEEL
tachyon_platform-0.2.1.dist-info/RECORD
