Metadata-Version: 2.4
Name: tachyon-platform
Version: 0.2.1
Summary: Tachyon Platform API SDK for Python
Requires-Python: >=3.11,<3.14
Classifier: Programming Language :: Python :: 3
Classifier: Programming Language :: Python :: 3.11
Classifier: Programming Language :: Python :: 3.12
Classifier: Programming Language :: Python :: 3.13
Requires-Dist: pydantic (>=2)
Requires-Dist: pyjwt[crypto] (>=2.8.0)
Requires-Dist: python-dateutil (>=2.8.2)
Requires-Dist: typing-extensions (>=4.7.1)
Requires-Dist: urllib3 (>=2.1.0,<3.0.0)
